source_and_license/__init__.py
source_and_license/source_license.py
source_and_license/modules/__init__.py
source_and_license-1.0.0.dist-info/LICENSE
source_and_license-1.0.0.dist-info/METADATA
source_and_license-1.0.0.dist-info/WHEEL
source_and_license-1.0.0.dist-info/top_level.txt
source_and_license-1.0.0.dist-info/RECORD
